pu_xu/IQ_set.py
pu_xu/VCIQcap.dll
pu_xu/__init__.py
pu_xu/xu_tde.dll
pu_xu/xu_tde.py
pu_xu/xu_tde_sample.py
pu_xu-2023.10.1.7.dist-info/METADATA
pu_xu-2023.10.1.7.dist-info/WHEEL
pu_xu-2023.10.1.7.dist-info/top_level.txt
pu_xu-2023.10.1.7.dist-info/RECORD
