Metadata-Version: 2.1
Name: pu-xu
Version: 2023.10.1.7
Summary: camera IQ setting and  xu command package
Home-page: UNKNOWN
Author: lorry_rui
Author-email: lrui@logitech.com
License: UNKNOWN
Platform: UNKNOWN
Classifier: Programming Language :: Python :: 3.6
Classifier: License :: OSI Approved :: MIT License
Classifier: Operating System :: OS Independent
Requires-Python: >=3.6
